.DS_Store
simple_distributions/Binomialdistribution.py
simple_distributions/Gaussiandistribution.py
simple_distributions/Generaldistribution.py
simple_distributions/__init__.py
simple_distributions-0.2.2.dist-info/METADATA
simple_distributions-0.2.2.dist-info/WHEEL
simple_distributions-0.2.2.dist-info/top_level.txt
simple_distributions-0.2.2.dist-info/RECORD
