Metadata-Version: 2.1
Name: simple-distributions
Version: 0.2.2
Summary: A package for calculating probability density functions of common statistical distributions using numerical data and visualizing the results.
Home-page: UNKNOWN
Author: Dave Rench McCauley
Author-email: drench56@gmail.com
License: UNKNOWN
Platform: UNKNOWN
